[
  {
    "ID": "hidden",
    "Name": "Hidden",
    "Description": "Find the secret area",
    "RequiredProgress": 1,
    "Rewards": {
      "reward_cores": 500
    }
  },
  {
    "ID": "easter_egg",
    "Name": "Easter Egg",
    "Description": "Discover the developer room",
    "RequiredProgress": 1,
    "Rewards": {
      "reward_legendary": 1
    }
  },
  {
    "ID": "lucky",
    "Name": "Lucky",
    "Description": "Get 3 Legendaries in one loot drop",
    "RequiredProgress": 1,
    "Rewards": {
      "reward_cores": 777
    }
  },
  {
    "ID": "pacifist",
    "Name": "Pacifist",
    "Description": "Complete a wave using only drones",
    "RequiredProgress": 1,
    "Rewards": {
      "reward_cores": 300
    }
  },
  {
    "ID": "iron_man",
    "Name": "Iron Man",
    "Description": "Complete Wave 20 with Common gear only",
    "RequiredProgress": 1,
    "Rewards": {
      "reward_legendary": 2
    }
  }
]
